urlspy/opengraph.py
urlspy/spy.py
urlspy-0.0.1.dist-info/WHEEL
urlspy-0.0.1.dist-info/METADATA
urlspy-0.0.1.dist-info/RECORD
